liman_openapi/__init__.py
liman_openapi/load.py
liman_openapi/operation.py
liman_openapi/parse.py
liman_openapi/py.typed
liman_openapi/schemas.py
liman_openapi/tool_node.py
liman_openapi/utils.py
liman_openapi-0.1.0a0.dist-info/METADATA
liman_openapi-0.1.0a0.dist-info/WHEEL
liman_openapi-0.1.0a0.dist-info/RECORD
