Metadata-Version: 2.4
Name: liman-openapi
Version: 0.1.0a0
Summary: Liman AgentOps OpenAPI Library
Author-email: Guro Bokum <jiojiajiu@gmail.com>
License-Expression: MIT
Classifier: License :: OSI Approved :: MIT License
Classifier: Operating System :: OS Independent
Classifier: Programming Language :: Python :: 3
Requires-Python: >=3.10
Requires-Dist: httpx>=0.28.1
Requires-Dist: liman-core
Requires-Dist: openapi-core>=0.19.5
Requires-Dist: openapi-spec-validator>=0.7.2
Requires-Dist: ruamel-yaml>=0.18.14
